[{"name":"process_action.action_controller","payload":{"controller":"RegistrationsController","action":"new","params":{"controller":"registrations","action":"new"},"headers":"Not JSON Encodable","format":"html","method":"GET","path":"/users/sign_up","view_runtime":null,"db_runtime":0,"exception":["NoMethodError","undefined method `role' for nil:NilClass"],"exception_object":"undefined method `role' for nil:NilClass","status":"500"},"time":"2017-04-16T22:26:36.367-04:00","transaction_id":"de952b0ebc22dccd5d7f","end":"2017-04-16T22:26:36.370-04:00","children":[],"duration":2.948},{"name":"process_action.action_controller.exception","payload":{"call":"NoMethodError (undefined method `role' for nil:NilClass)"},"time":0,"transaction_id":null,"end":0,"children":[],"duration":0.0},{"name":"process_action.action_controller.exception","payload":{"call":"app/controllers/registrations_controller.rb:151:in `authorize_admin'"},"time":0,"transaction_id":null,"end":0,"children":[],"duration":0.0}]